{
  "result": {
    "what_description": "Population distributed by religious affiliation such as Buddhist, Hindu, Islam, and Christian",
    "when_description": "2012",
    "where_description": "Grama Niladhari Divisions in LK-1127",
    "how_description": "Map",
    "image_path": "/tmp/lanka_data/images/Religion_2012_LK-1127:gnd_Map.png",
    "source": "Department of Census and Statistics, Sri Lanka",
    "source_url": "https://www.statistics.gov.lk/",
    "cmd": "Religion/2012/LK-1127:gnd/Map"
  },
  "query_time_ms": 0,
  "cache_hit": false
}